openai_finetuner-0.2.2.dist-info/METADATA
openai_finetuner-0.2.2.dist-info/WHEEL
openai_finetuner-0.2.2.dist-info/entry_points.txt
openai_finetuner/__init__.py
openai_finetuner/client/openai/__init__.py
openai_finetuner/client/openai/client.py
openai_finetuner/client/openai/cost.py
openai_finetuner/client/openai/key.py
openai_finetuner/client/openai/types.py
openai_finetuner/client/openai/validate.py
openai_finetuner/client/wrappers/cache.py
openai_finetuner/constants.py
openai_finetuner/core/interfaces.py
openai_finetuner/core/types.py
openai_finetuner/dataset.py
openai_finetuner/experiment.py
openai_finetuner/util/hash.py
openai_finetuner-0.2.2.dist-info/RECORD
